fiftyone_devicedetection_shared/__init__.py
fiftyone_devicedetection_shared/constants.py
fiftyone_devicedetection_shared/example_constants.py
fiftyone_devicedetection_shared/key_utils.py
fiftyone_devicedetection_shared/utils.py
fiftyone_devicedetection_shared-4.5.18.dist-info/METADATA
fiftyone_devicedetection_shared-4.5.18.dist-info/WHEEL
fiftyone_devicedetection_shared-4.5.18.dist-info/top_level.txt
fiftyone_devicedetection_shared-4.5.18.dist-info/RECORD
