Metadata-Version: 2.4
Name: fiftyone_devicedetection_shared
Version: 4.5.18
Summary: The 51Degrees Pipeline API is a generic web request intelligence and data processing solution with the ability to add a range of 51Degrees and/or custom plug ins (Engines). This project contains 51Degrees Device Detection engines that can be used with the Pipeline API.
Home-page: https://51degrees.com/
Author: 51Degrees Engineering
Author-email: engineering@51degrees.com
License: EUPL-1.2
Classifier: Development Status :: 5 - Production/Stable
Classifier: Programming Language :: Python
Classifier: License :: OSI Approved :: European Union Public Licence 1.2 (EUPL 1.2)
Classifier: Operating System :: OS Independent
Classifier: Topic :: Software Development :: Libraries :: Python Modules
Requires-Python: >=3.8
Requires-Dist: fiftyone_pipeline_core
Requires-Dist: fiftyone_pipeline_engines
Requires-Dist: fiftyone_pipeline_cloudrequestengine
Requires-Dist: fiftyone_pipeline_engines_fiftyone
Dynamic: author
Dynamic: author-email
Dynamic: classifier
Dynamic: description
Dynamic: description-content-type
Dynamic: home-page
Dynamic: license
Dynamic: requires-dist
Dynamic: requires-python
Dynamic: summary
